Metadata-Version: 2.1
Name: NeuNet
Version: 0.0.2
Summary: Python
Home-page: 
Author: Pranav Sai
Author-email: pranavs31899@gmail.com
License: MIT
Keywords: Neural Network
Platform: UNKNOWN
Classifier: Development Status :: 5 - Production/Stable
Classifier: Intended Audience :: Education
Classifier: Operating System :: Microsoft :: Windows :: Windows 10
Classifier: License :: OSI Approved :: MIT License
Classifier: Programming Language :: Python :: 3
License-File: LICENCE.txt
